{
    "id": 170,
    "nome": "Imobilizar Pessoa",
    "nivel": 2,
    "classes": [
        "Bardo",
        "Bruxo",
        "Clérigo",
        "Druida",
        "Feiticeiro",
        "Mago"
    ],
    "escola": "Encantamento",
    "ritual": false,
    "tempoConjuracao": "1 ação",
    "alcance": "18 metros",
    "componentes": "Verbal, Somático, Material (uma pequena peça de ferro reta)",
    "duracao": "Concentração, até 1 minuto",
    "descricao": "Escolha um humanoide que você possa ver, dentro do alcance. O alvo deve ser bem sucedido num teste de resistência de Sabedoria ou ficará paralisado pela duração. Essa magia não tem efeito em mortos-vivos. No final de cada um dos turnos dele, o alvo pode realizar outro teste de resistência de Sabedoria. Se obtiver sucesso, a magia termina no alvo. Em Níveis Superiores . Quando você conjurar essa magia usando um espaço de magia de 3° nível ou superior, você pode afetar um humanoide adicional para cada nível de magia acima do 2°. Os humanoides devem estar a 9 metros entre si para serem afetados."
}