{"escola":"Adivinhação","ritual":false,"classes":["Bardo","Bruxo","Feiticeiro","Mago"],"id":26,"nivel":0,"duracao":"Concentração, até 1 rodada","nome":"Ataque Certeiro","tempoConjuracao":"1 ação","alcance":"9 metros","descricao":"Você estende sua mão e aponta o dedo para um alvo no alcance. Sua magia garante a você uma breve intuição sobre as defesas do alvo. No seu próximo turno, você terá vantagem na primeira jogada de ataque contra o alvo, considerando que essa magia não tenha acabado.","componentes":"Somático"}