{"escola":"Adivinhação","ritual":false,"classes":["Bardo","Clérigo","Druida","Feiticeiro","Mago"],"id":327,"nivel":5,"duracao":"Concentração, até 10 minutos","nome":"Vidência","tempoConjuracao":"10 minutos","alcance":"Pessoal","descricao":"Você pode ver e ouvir uma criatura em particular, à sua escolha, que esteja no mesmo plano de existência que você. O alvo deve realizar um teste de resistência de Sabedoria, que é modificador de acordo com o quão bem você conhece o alvo e o tipo de conexão física que você tem com ele. Se um alvo souber que você está conjurando essa magia, ele pode falhar no teste de resistência voluntariamente, se ele quiser ser observado.\nCom um sucesso na resistência, o alvo não é afetado e você não pode usar essa magia contra ele novamente por 24 horas.\nSe falhar na resistência, a magia cria um sensor invisível a até 3 metros do alvo. Você pode ver e ouvir através do sensor, como se você estivesse onde ele está. O sensor se move com o alvo, permanecendo a 3 metros dele pela duração. Uma criatura que puder ver objetos invisíveis verá o sensor como um globo luminoso do tamanho de um punho.\nAo invés de focar em uma criatura, você pode escolher um local que você já tenha visto antes como alvo dessa magia. Quando fizer isso, o sensor aparece no local e não se move.\n\n——————————————————\n\nCONHECIMENTO\nSegunda mão (Você ouviu falar do alvo)\nModificador de Resistência -> +5\n\nPrimeira mão (Você foi apresentado ao alvo)\nModificador de Resistência -> +0\n\nFamiliar (Você conhece bem o alvo)\nModificador de Resistência -> -5\n\n——————————————————\n\nCONEXÃO\nDescrição ou foto\nModificador de Resistência -> -2\n\nPertences ou roupas\nModificador de Resistência -> -4\n\nParte do corpo, mexa de cabelo, recorte de unha ou similar\nModificador de Resistência -> -10\n\n——————————————————","componentes":"Verbal, Somático, Material (um foco valendo, no mínimo, 1.000 po, como uma bola de cristal, espelho de prata ou fonte cheia de água benta)"}